evolve/__init__.py
evolve/battery/__init__.py
evolve/battery/battery.py
evolve/battery/peak_shaving_strategy.py
evolve/battery/self_consumption_strategy.py
evolve/battery/timed_strategy.py
evolve/ev/__init__.py
evolve/ev/ev_constants.py
evolve/ev/ev_interfaces.py
evolve/ev/ev_module.py
evolve/solar/__init__.py
evolve/solar/solar.py
evolve_core-1.0.3.dist-info/METADATA
evolve_core-1.0.3.dist-info/WHEEL
evolve_core-1.0.3.dist-info/RECORD
