Metadata-Version: 2.1
Name: evolve-core
Version: 1.0.3
Summary: Modern tool for understanding impact of distributed energy resources on net load.
Project-URL: Homepage, https://github.com/NREL/evolve
Author-email: Kapil Duwadi <kapil.duwadi@nrel.gov>, Erik Pohl <erik.pohl@nrel.gov>
License-Expression: BSD-3-Clause
Keywords: Distribution,Electric,Energy,Net,PV,Storage,System,Vehicle,load
Classifier: License :: OSI Approved :: BSD License
Classifier: Operating System :: OS Independent
Classifier: Programming Language :: Python :: 3.10
Requires-Python: >=3.10
Requires-Dist: numpy
Requires-Dist: polars
Requires-Dist: pvlib
Requires-Dist: pydantic
Requires-Dist: pytest
Requires-Dist: timezonefinder
